osmanthus/__init__.py
osmanthus/cli.py
osmanthus/engine.py
osmanthus/evaluate.py
osmanthus/performance.bin
osmanthus-0.1.4.dist-info/LICENSE
osmanthus-0.1.4.dist-info/METADATA
osmanthus-0.1.4.dist-info/WHEEL
osmanthus-0.1.4.dist-info/entry_points.txt
osmanthus-0.1.4.dist-info/top_level.txt
osmanthus-0.1.4.dist-info/RECORD
