Metadata-Version: 2.1
Name: osmanthus
Version: 0.1.4
Summary: An algorithmic chess engine, written in Python.
Author: Ian Breckenridge
Project-URL: Repository, https://github.com/i13e/osmanthus
Project-URL: Documentation, https://github.com/i13e/osmanthus/wiki
Project-URL: Issues, https://github.com/i13e/osmanthus/issues
Keywords: chess
Classifier: Development Status :: 4 - Beta
Classifier: License :: OSI Approved :: GNU General Public License v3 or later (GPLv3+)
Classifier: Programming Language :: Python
Classifier: Programming Language :: Python :: 3.9
Classifier: Programming Language :: Python :: 3.10
Classifier: Programming Language :: Python :: 3.11
Classifier: Programming Language :: Python :: Implementation :: CPython
Classifier: Topic :: Games/Entertainment :: Board Games
Classifier: Topic :: Games/Entertainment :: Turn Based Strategy
Classifier: Typing :: Typed
Requires-Python: >=3.9
License-File: LICENSE
Requires-Dist: chess==1.11.1
